pysnid/__init__.py
pysnid/snid.py
pysnid/tools.py
pysnid-0.6.0.dist-info/licenses/LICENSE
pysnid-0.6.0.dist-info/METADATA
pysnid-0.6.0.dist-info/WHEEL
pysnid-0.6.0.dist-info/top_level.txt
pysnid-0.6.0.dist-info/RECORD
